com/phida/main/Operations.py
com/phida/main/SilverMerge.py
com/phida/main/__init__.py
com/phida/main/config.py
com/phida/main/logging.py
com/phida/main/sparksession.py
com/phida/main/utils.py
com/phida/tests/OperationsTest.py
com/phida/tests/__init__.py
com/phida/tests/main_test.py
com/phida/tests/utils_test.py
SilverStreamingApplicationPoC-1.24.dist-info/METADATA
SilverStreamingApplicationPoC-1.24.dist-info/WHEEL
SilverStreamingApplicationPoC-1.24.dist-info/top_level.txt
SilverStreamingApplicationPoC-1.24.dist-info/RECORD
