Metadata-Version: 2.1
Name: SilverStreamingApplicationPoC
Version: 1.24
Summary: For Demo
Home-page: UNKNOWN
Author: 
Author-email: 
License: UNKNOWN
Platform: UNKNOWN
